MANIFEST.in
README.md
setup.py
TOPSIS_Sunidhi_101983052/__init__.py
TOPSIS_Sunidhi_101983052/topsis.py
topsis_sunidhi.egg-info/PKG-INFO
topsis_sunidhi.egg-info/SOURCES.txt
topsis_sunidhi.egg-info/dependency_links.txt
topsis_sunidhi.egg-info/entry_points.txt
topsis_sunidhi.egg-info/requires.txt
topsis_sunidhi.egg-info/top_level.txt