Metadata-Version: 1.1
Name: topsis-sunidhi
Version: 2.0.0
Summary: A python package to implement TOPSIS on a given dataset
Home-page: https://github.com/SunidhiSingla/TOPSIS-Sunidhi-101983052
Author: Sunidhi
Author-email: ssunidhi1_be18@thapar.edu
License: MIT
Platform: UNKNOWN
Classifier: License :: OSI Approved :: MIT License
Classifier: Programming Language :: Python :: 3
Classifier: Programming Language :: Python :: 3.4
Classifier: Programming Language :: Python :: 3.5
Classifier: Programming Language :: Python :: 3.6
Classifier: Programming Language :: Python :: 3.7
